{"savedAt":1784200483319,"value":{"result":{"entryCount":6,"entries":[{"map":"5-2","node":"F","mainFleet":[{"id":1579,"name":"空母ヲ級","name_en":"Wo-Class Standard Carrier","lvl":1,"hp":96,"fp":25,"aa":50,"armor":80,"equips":[1547,1548,1549,1549,-1]},{"id":1527,"name":"重巡リ級","name_en":"Ri-Class Heavy Cruiser","lvl":1,"hp":76,"fp":68,"torp":48,"aa":40,"armor":70,"equips":[1505,1506,1515,1525,-1]},{"id":1527,"name":"重巡リ級","name_en":"Ri-Class Heavy Cruiser","lvl":1,"hp":76,"fp":68,"torp":48,"aa":40,"armor":70,"equips":[1505,1506,1515,1525,-1]},{"id":1555,"name":"軽巡ヘ級","name_en":"He-Class Light Cruiser","lvl":1,"hp":57,"fp":48,"torp":80,"aa":30,"armor":39,"equips":[1506,1525,1542,1543,-1]},{"id":1576,"name":"駆逐ロ級後期型","name_en":"Ro-Class Destroyer{ -}? Late Model","lvl":1,"hp":37,"fp":38,"torp":66,"aa":32,"armor":26,"equips":[1502,1545,1542,-1,-1]},{"id":1576,"name":"駆逐ロ級後期型","name_en":"Ro-Class Destroyer{ -}? Late Model","lvl":1,"hp":37,"fp":38,"torp":66,"aa":32,"armor":26,"equips":[1502,1545,1542,-1,-1]}],"escortFleet":[],"formation":3,"count":3807,"airpower":[29,57,126,252],"lbasAirpower":[30,60,134,267],"uncertainAirpowerItems":[],"masterId":114985775},{"map":"5-2","node":"F","mainFleet":[{"id":1579,"name":"空母ヲ級","name_en":"Wo-Class Standard Carrier","lvl":1,"hp":96,"fp":25,"aa":50,"armor":80,"equips":[1547,1548,1549,1549,-1]},{"id":1527,"name":"重巡リ級","name_en":"Ri-Class Heavy Cruiser","lvl":1,"hp":76,"fp":68,"torp":48,"aa":40,"armor":70,"equips":[1505,1506,1515,1525,-1]},{"id":1527,"name":"重巡リ級","name_en":"Ri-Class Heavy Cruiser","lvl":1,"hp":76,"fp":68,"torp":48,"aa":40,"armor":70,"equips":[1505,1506,1515,1525,-1]},{"id":1555,"name":"軽巡ヘ級","name_en":"He-Class Light Cruiser","lvl":1,"hp":57,"fp":48,"torp":80,"aa":30,"armor":39,"equips":[1506,1525,1542,1543,-1]},{"id":1576,"name":"駆逐ロ級後期型","name_en":"Ro-Class Destroyer{ -}? Late Model","lvl":1,"hp":37,"fp":38,"torp":66,"aa":32,"armor":26,"equips":[1502,1545,1542,-1,-1]},{"id":1576,"name":"駆逐ロ級後期型","name_en":"Ro-Class Destroyer{ -}? Late Model","lvl":1,"hp":37,"fp":38,"torp":66,"aa":32,"armor":26,"equips":[1502,1545,1542,-1,-1]}],"escortFleet":[],"formation":2,"count":1591,"airpower":[29,57,126,252],"lbasAirpower":[30,60,134,267],"uncertainAirpowerItems":[],"masterId":115005001},{"map":"5-2","node":"F","mainFleet":[{"id":1579,"name":"空母ヲ級","name_en":"Wo-Class Standard Carrier","lvl":1,"hp":96,"fp":25,"aa":50,"armor":80,"equips":[1547,1548,1549,1549,-1]},{"id":1527,"name":"重巡リ級","name_en":"Ri-Class Heavy Cruiser","lvl":1,"hp":76,"fp":68,"torp":48,"aa":40,"armor":70,"equips":[1505,1506,1515,1525,-1]},{"id":1555,"name":"軽巡ヘ級","name_en":"He-Class Light Cruiser","lvl":1,"hp":57,"fp":48,"torp":80,"aa":30,"armor":39,"equips":[1506,1525,1542,1543,-1]},{"id":1576,"name":"駆逐ロ級後期型","name_en":"Ro-Class Destroyer{ -}? Late Model","lvl":1,"hp":37,"fp":38,"torp":66,"aa":32,"armor":26,"equips":[1502,1545,1542,-1,-1]},{"id":1576,"name":"駆逐ロ級後期型","name_en":"Ro-Class Destroyer{ -}? Late Model","lvl":1,"hp":37,"fp":38,"torp":66,"aa":32,"armor":26,"equips":[1502,1545,1542,-1,-1]},{"id":1576,"name":"駆逐ロ級後期型","name_en":"Ro-Class Destroyer{ -}? Late Model","lvl":1,"hp":37,"fp":38,"torp":66,"aa":32,"armor":26,"equips":[1502,1545,1542,-1,-1]}],"escortFleet":[],"formation":3,"count":3063,"airpower":[29,57,126,252],"lbasAirpower":[30,59,131,261],"uncertainAirpowerItems":[],"masterId":114981192},{"map":"5-2","node":"F","mainFleet":[{"id":1579,"name":"空母ヲ級","name_en":"Wo-Class Standard Carrier","lvl":1,"hp":96,"fp":25,"aa":50,"armor":80,"equips":[1547,1548,1549,1549,-1]},{"id":1527,"name":"重巡リ級","name_en":"Ri-Class Heavy Cruiser","lvl":1,"hp":76,"fp":68,"torp":48,"aa":40,"armor":70,"equips":[1505,1506,1515,1525,-1]},{"id":1555,"name":"軽巡ヘ級","name_en":"He-Class Light Cruiser","lvl":1,"hp":57,"fp":48,"torp":80,"aa":30,"armor":39,"equips":[1506,1525,1542,1543,-1]},{"id":1576,"name":"駆逐ロ級後期型","name_en":"Ro-Class Destroyer{ -}? Late Model","lvl":1,"hp":37,"fp":38,"torp":66,"aa":32,"armor":26,"equips":[1502,1545,1542,-1,-1]},{"id":1576,"name":"駆逐ロ級後期型","name_en":"Ro-Class Destroyer{ -}? Late Model","lvl":1,"hp":37,"fp":38,"torp":66,"aa":32,"armor":26,"equips":[1502,1545,1542,-1,-1]},{"id":1576,"name":"駆逐ロ級後期型","name_en":"Ro-Class Destroyer{ -}? Late Model","lvl":1,"hp":37,"fp":38,"torp":66,"aa":32,"armor":26,"equips":[1502,1545,1542,-1,-1]}],"escortFleet":[],"formation":2,"count":1561,"airpower":[29,57,126,252],"lbasAirpower":[30,59,131,261],"uncertainAirpowerItems":[],"masterId":114987526},{"map":"5-2","node":"F","mainFleet":[{"id":1579,"name":"空母ヲ級","name_en":"Wo-Class Standard Carrier","lvl":1,"hp":96,"fp":25,"aa":50,"armor":80,"equips":[1547,1548,1549,1549,-1]},{"id":1527,"name":"重巡リ級","name_en":"Ri-Class Heavy Cruiser","lvl":1,"hp":76,"fp":68,"torp":48,"aa":40,"armor":70,"equips":[1505,1506,1515,1525,-1]},{"id":1554,"name":"軽巡ホ級","name_en":"Ho-Class Light Cruiser","lvl":1,"hp":53,"fp":42,"torp":72,"aa":27,"armor":36,"equips":[1504,1542,1543,-1,-1]},{"id":1576,"name":"駆逐ロ級後期型","name_en":"Ro-Class Destroyer{ -}? Late Model","lvl":1,"hp":37,"fp":38,"torp":66,"aa":32,"armor":26,"equips":[1502,1545,1542,-1,-1]},{"id":1576,"name":"駆逐ロ級後期型","name_en":"Ro-Class Destroyer{ -}? Late Model","lvl":1,"hp":37,"fp":38,"torp":66,"aa":32,"armor":26,"equips":[1502,1545,1542,-1,-1]},{"id":1576,"name":"駆逐ロ級後期型","name_en":"Ro-Class Destroyer{ -}? Late Model","lvl":1,"hp":37,"fp":38,"torp":66,"aa":32,"armor":26,"equips":[1502,1545,1542,-1,-1]}],"escortFleet":[],"formation":3,"count":3822,"airpower":[29,57,126,252],"lbasAirpower":[29,58,129,258],"uncertainAirpowerItems":[],"masterId":114981285},{"map":"5-2","node":"F","mainFleet":[{"id":1579,"name":"空母ヲ級","name_en":"Wo-Class Standard Carrier","lvl":1,"hp":96,"fp":25,"aa":50,"armor":80,"equips":[1547,1548,1549,1549,-1]},{"id":1527,"name":"重巡リ級","name_en":"Ri-Class Heavy Cruiser","lvl":1,"hp":76,"fp":68,"torp":48,"aa":40,"armor":70,"equips":[1505,1506,1515,1525,-1]},{"id":1554,"name":"軽巡ホ級","name_en":"Ho-Class Light Cruiser","lvl":1,"hp":53,"fp":42,"torp":72,"aa":27,"armor":36,"equips":[1504,1542,1543,-1,-1]},{"id":1576,"name":"駆逐ロ級後期型","name_en":"Ro-Class Destroyer{ -}? Late Model","lvl":1,"hp":37,"fp":38,"torp":66,"aa":32,"armor":26,"equips":[1502,1545,1542,-1,-1]},{"id":1576,"name":"駆逐ロ級後期型","name_en":"Ro-Class Destroyer{ -}? Late Model","lvl":1,"hp":37,"fp":38,"torp":66,"aa":32,"armor":26,"equips":[1502,1545,1542,-1,-1]},{"id":1576,"name":"駆逐ロ級後期型","name_en":"Ro-Class Destroyer{ -}? Late Model","lvl":1,"hp":37,"fp":38,"torp":66,"aa":32,"armor":26,"equips":[1502,1545,1542,-1,-1]}],"escortFleet":[],"formation":2,"count":1505,"airpower":[29,57,126,252],"lbasAirpower":[29,58,129,258],"uncertainAirpowerItems":[],"masterId":114983181}]},"retrieved":"2026-07-16T20:32:56+09:00"}}