{"savedAt":1784200483319,"value":{"result":{"entryCount":6,"entries":[{"map":"7-5","node":"E","mainFleet":[{"id":1575,"name":"駆逐イ級後期型","name_en":"I-Class Destroyer{ -}? Late Model","lvl":1,"hp":35,"fp":38,"torp":60,"aa":30,"armor":22,"equips":[1502,1545,1542,-1,-1]},{"id":1575,"name":"駆逐イ級後期型","name_en":"I-Class Destroyer{ -}? Late Model","lvl":1,"hp":35,"fp":38,"torp":60,"aa":30,"armor":22,"equips":[1502,1545,1542,-1,-1]},{"id":1640,"name":"PT小鬼群","name_en":"PT Imp Pack","lvl":1,"hp":18,"fp":18,"torp":118,"aa":24,"armor":39,"equips":[1515,1515,-1,-1,-1]},{"id":1639,"name":"PT小鬼群","name_en":"PT Imp Pack","lvl":1,"hp":15,"fp":15,"torp":98,"aa":18,"armor":29,"equips":[1515,1515,-1,-1,-1]},{"id":1638,"name":"PT小鬼群","name_en":"PT Imp Pack","lvl":1,"hp":9,"fp":9,"torp":98,"aa":18,"armor":29,"equips":[1515,1515,-1,-1,-1]},{"id":1637,"name":"PT小鬼群","name_en":"PT Imp Pack","lvl":1,"hp":9,"fp":9,"torp":88,"aa":12,"armor":19,"equips":[1515,-1,-1,-1,-1]}],"escortFleet":[],"formation":1,"count":16,"airpower":[0,0,0,0],"lbasAirpower":[0,0,0,0],"uncertainAirpowerItems":[],"masterId":121483659},{"map":"7-5","node":"E","mainFleet":[{"id":1575,"name":"駆逐イ級後期型","name_en":"I-Class Destroyer{ -}? Late Model","lvl":1,"hp":35,"fp":38,"torp":60,"aa":30,"armor":22,"equips":[1502,1545,1542,-1,-1]},{"id":1501,"name":"駆逐イ級","name_en":"I-Class Destroyer","lvl":1,"hp":20,"fp":5,"torp":15,"aa":6,"armor":5,"equips":[1501,-1,-1,-1,-1]},{"id":1639,"name":"PT小鬼群","name_en":"PT Imp Pack","lvl":1,"hp":15,"fp":15,"torp":98,"aa":18,"armor":29,"equips":[1515,1515,-1,-1,-1]},{"id":1638,"name":"PT小鬼群","name_en":"PT Imp Pack","lvl":1,"hp":9,"fp":9,"torp":98,"aa":18,"armor":29,"equips":[1515,1515,-1,-1,-1]},{"id":1637,"name":"PT小鬼群","name_en":"PT Imp Pack","lvl":1,"hp":9,"fp":9,"torp":88,"aa":12,"armor":19,"equips":[1515,-1,-1,-1,-1]},{"id":1637,"name":"PT小鬼群","name_en":"PT Imp Pack","lvl":1,"hp":9,"fp":9,"torp":88,"aa":12,"armor":19,"equips":[1515,-1,-1,-1,-1]}],"escortFleet":[],"formation":1,"count":11,"airpower":[0,0,0,0],"lbasAirpower":[0,0,0,0],"uncertainAirpowerItems":[],"masterId":121630065},{"map":"7-5","node":"E","mainFleet":[{"id":1575,"name":"駆逐イ級後期型","name_en":"I-Class Destroyer{ -}? Late Model","lvl":1,"hp":35,"fp":38,"torp":60,"aa":30,"armor":22,"equips":[1502,1545,1542,-1,-1]},{"id":1575,"name":"駆逐イ級後期型","name_en":"I-Class Destroyer{ -}? Late Model","lvl":1,"hp":35,"fp":38,"torp":60,"aa":30,"armor":22,"equips":[1502,1545,1542,-1,-1]},{"id":1639,"name":"PT小鬼群","name_en":"PT Imp Pack","lvl":1,"hp":15,"fp":15,"torp":98,"aa":18,"armor":29,"equips":[1515,1515,-1,-1,-1]},{"id":1638,"name":"PT小鬼群","name_en":"PT Imp Pack","lvl":1,"hp":9,"fp":9,"torp":98,"aa":18,"armor":29,"equips":[1515,1515,-1,-1,-1]},{"id":1637,"name":"PT小鬼群","name_en":"PT Imp Pack","lvl":1,"hp":9,"fp":9,"torp":88,"aa":12,"armor":19,"equips":[1515,-1,-1,-1,-1]}],"escortFleet":[],"formation":6,"count":16,"airpower":[0,0,0,0],"lbasAirpower":[0,0,0,0],"uncertainAirpowerItems":[],"masterId":121488201},{"map":"7-5","node":"E","mainFleet":[{"id":1575,"name":"駆逐イ級後期型","name_en":"I-Class Destroyer{ -}? Late Model","lvl":1,"hp":35,"fp":38,"torp":60,"aa":30,"armor":22,"equips":[1502,1545,1542,-1,-1]},{"id":1575,"name":"駆逐イ級後期型","name_en":"I-Class Destroyer{ -}? Late Model","lvl":1,"hp":35,"fp":38,"torp":60,"aa":30,"armor":22,"equips":[1502,1545,1542,-1,-1]},{"id":1639,"name":"PT小鬼群","name_en":"PT Imp Pack","lvl":1,"hp":15,"fp":15,"torp":98,"aa":18,"armor":29,"equips":[1515,1515,-1,-1,-1]},{"id":1638,"name":"PT小鬼群","name_en":"PT Imp Pack","lvl":1,"hp":9,"fp":9,"torp":98,"aa":18,"armor":29,"equips":[1515,1515,-1,-1,-1]},{"id":1637,"name":"PT小鬼群","name_en":"PT Imp Pack","lvl":1,"hp":9,"fp":9,"torp":88,"aa":12,"armor":19,"equips":[1515,-1,-1,-1,-1]}],"escortFleet":[],"formation":1,"count":36,"airpower":[0,0,0,0],"lbasAirpower":[0,0,0,0],"uncertainAirpowerItems":[],"masterId":121485821},{"map":"7-5","node":"E","mainFleet":[{"id":1575,"name":"駆逐イ級後期型","name_en":"I-Class Destroyer{ -}? Late Model","lvl":1,"hp":35,"fp":38,"torp":60,"aa":30,"armor":22,"equips":[1502,1545,1542,-1,-1]},{"id":1501,"name":"駆逐イ級","name_en":"I-Class Destroyer","lvl":1,"hp":20,"fp":5,"torp":15,"aa":6,"armor":5,"equips":[1501,-1,-1,-1,-1]},{"id":1639,"name":"PT小鬼群","name_en":"PT Imp Pack","lvl":1,"hp":15,"fp":15,"torp":98,"aa":18,"armor":29,"equips":[1515,1515,-1,-1,-1]},{"id":1638,"name":"PT小鬼群","name_en":"PT Imp Pack","lvl":1,"hp":9,"fp":9,"torp":98,"aa":18,"armor":29,"equips":[1515,1515,-1,-1,-1]},{"id":1637,"name":"PT小鬼群","name_en":"PT Imp Pack","lvl":1,"hp":9,"fp":9,"torp":88,"aa":12,"armor":19,"equips":[1515,-1,-1,-1,-1]}],"escortFleet":[],"formation":6,"count":9,"airpower":[0,0,0,0],"lbasAirpower":[0,0,0,0],"uncertainAirpowerItems":[],"masterId":121680098},{"map":"7-5","node":"E","mainFleet":[{"id":1575,"name":"駆逐イ級後期型","name_en":"I-Class Destroyer{ -}? Late Model","lvl":1,"hp":35,"fp":38,"torp":60,"aa":30,"armor":22,"equips":[1502,1545,1542,-1,-1]},{"id":1501,"name":"駆逐イ級","name_en":"I-Class Destroyer","lvl":1,"hp":20,"fp":5,"torp":15,"aa":6,"armor":5,"equips":[1501,-1,-1,-1,-1]},{"id":1639,"name":"PT小鬼群","name_en":"PT Imp Pack","lvl":1,"hp":15,"fp":15,"torp":98,"aa":18,"armor":29,"equips":[1515,1515,-1,-1,-1]},{"id":1638,"name":"PT小鬼群","name_en":"PT Imp Pack","lvl":1,"hp":9,"fp":9,"torp":98,"aa":18,"armor":29,"equips":[1515,1515,-1,-1,-1]},{"id":1637,"name":"PT小鬼群","name_en":"PT Imp Pack","lvl":1,"hp":9,"fp":9,"torp":88,"aa":12,"armor":19,"equips":[1515,-1,-1,-1,-1]}],"escortFleet":[],"formation":1,"count":24,"airpower":[0,0,0,0],"lbasAirpower":[0,0,0,0],"uncertainAirpowerItems":[],"masterId":121492783}]},"retrieved":"2026-07-16T20:46:34+09:00"}}