{"savedAt":1784200483319,"value":{"result":{"route":{"0":[null,"1",0,0],"1":["1","A",4,4],"2":["1","B",2,2],"3":["B","C",4,4],"4":["A","D",4,4],"5":["A","E",5,5],"6":["D","E",5,5]},"spots":{"1":[180,246,"Start"],"A":[491,171,null],"B":[505,328,null],"C":[709,500,null],"D":[809,171,null],"E":[968,362,null]},"mapSet":{"map":{"labels":[],"spots":[{"x":180,"y":246},{"line":{"x":-264,"y":2},"no":1,"x":491,"y":171},{"line":{"x":-270,"y":-72},"no":2,"x":505,"y":328},{"line":{"x":-185,"y":-156},"no":3,"x":709,"y":500},{"line":{"x":-295,"y":-4},"no":4,"x":809,"y":171},{"line":{"x":-456,"y":-181},"no":5,"x":968,"y":362},{"line":{"x":-148,"y":-176},"no":6,"x":968,"y":362}],"enemies":[],"airraids":[]},"frameSet":{"frames":{"map00102_map1-2":{"frame":{"w":1200,"h":720},"spriteSourceSize":{"w":1200,"h":720},"sourceSize":{"w":1200,"h":720}},"map00102_map1-2_point":{"frame":{"x":1205,"w":1200,"h":720},"spriteSourceSize":{"w":1200,"h":720},"sourceSize":{"w":1200,"h":720}},"map00102_route_1":{"frame":{"x":954,"y":725,"w":241,"h":64},"spriteSourceSize":{"w":241,"h":64},"sourceSize":{"w":241,"h":64}},"map00102_route_2":{"frame":{"x":710,"y":725,"w":239,"h":68},"spriteSourceSize":{"w":239,"h":68},"sourceSize":{"w":239,"h":68}},"map00102_route_3":{"frame":{"x":418,"y":725,"w":163,"h":140},"spriteSourceSize":{"w":163,"h":140},"sourceSize":{"w":163,"h":140}},"map00102_route_4":{"frame":{"x":1200,"y":725,"w":271,"h":6},"spriteSourceSize":{"w":271,"h":6},"sourceSize":{"w":271,"h":6}},"map00102_route_5":{"frame":{"y":725,"w":413,"h":172},"spriteSourceSize":{"w":413,"h":172},"sourceSize":{"w":413,"h":172}},"map00102_route_6":{"frame":{"x":586,"y":725,"w":119,"h":140},"spriteSourceSize":{"w":119,"h":140},"sourceSize":{"w":119,"h":140}}}},"breakpoints":[]}},"retrieved":"2026-07-16T20:14:43+09:00"}}